{"status":"OK","data":{"id":3049095,"identifier":"DVN/ZC7SMZ","persistentUrl":"https://doi.org/10.7910/DVN/ZC7SMZ","protocol":"doi","authority":"10.7910","publisher":"Harvard Dataverse","publicationDate":"2017-08-28","storageIdentifier":"s3://dvn-cloud:10.7910/DVN/ZC7SMZ","latestVersion":{"id":128384,"storageIdentifier":"s3://dvn-cloud:10.7910/DVN/ZC7SMZ","versionNumber":1,"versionMinorNumber":0,"versionState":"RELEASED","productionDate":"Production Date","UNF":"UNF:6:Rcxm+YVWOPys2uGGG3jISg==","lastUpdateTime":"2017-08-28T19:26:43Z","releaseTime":"2017-08-28T19:26:43Z","createTime":"2017-08-24T03:41:47Z","license":"CC0","termsOfUse":"CC0 Waiver","metadataBlocks":{"citation":{"displayName":"Citation Metadata","fields":[{"typeName":"title","multiple":false,"typeClass":"primitive","value":"MEDW 2014 Spanish European Election Study"},{"typeName":"author","multiple":true,"typeClass":"compound","value":[{"authorName":{"typeName":"authorName","multiple":false,"typeClass":"primitive","value":"Lago, Ignacio"},"authorAffiliation":{"typeName":"authorAffiliation","multiple":false,"typeClass":"primitive","value":"Pompeu Fabra University"}},{"authorName":{"typeName":"authorName","multiple":false,"typeClass":"primitive","value":"Bermúdez, Sandra"},"authorAffiliation":{"typeName":"authorAffiliation","multiple":false,"typeClass":"primitive","value":"Pompeu Fabra University"}},{"authorName":{"typeName":"authorName","multiple":false,"typeClass":"primitive","value":" Guinjoan, Marc"},"authorAffiliation":{"typeName":"authorAffiliation","multiple":false,"typeClass":"primitive","value":"Autonomous University of Barcelona"}},{"authorName":{"typeName":"authorName","multiple":false,"typeClass":"primitive","value":"Kelly Rowe"},"authorAffiliation":{"typeName":"authorAffiliation","multiple":false,"typeClass":"primitive","value":"Pompeu Fabra University"}},{"authorName":{"typeName":"authorName","multiple":false,"typeClass":"primitive","value":"Blais, André"},"authorAffiliation":{"typeName":"authorAffiliation","multiple":false,"typeClass":"primitive","value":"University of Montreal"}},{"authorName":{"typeName":"authorName","multiple":false,"typeClass":"primitive","value":"Stephenson, Laura"},"authorAffiliation":{"typeName":"authorAffiliation","multiple":false,"typeClass":"primitive","value":"University of Western Ontario"}}]},{"typeName":"datasetContact","multiple":true,"typeClass":"compound","value":[{"datasetContactName":{"typeName":"datasetContactName","multiple":false,"typeClass":"primitive","value":"Blais, André"},"datasetContactAffiliation":{"typeName":"datasetContactAffiliation","multiple":false,"typeClass":"primitive","value":"University of Montreal"},"datasetContactEmail":{"typeName":"datasetContactEmail","multiple":false,"typeClass":"primitive","value":"andre.blais@umontreal.ca"}}]},{"typeName":"dsDescription","multiple":true,"typeClass":"compound","value":[{"dsDescriptionValue":{"typeName":"dsDescriptionValue","multiple":false,"typeClass":"primitive","value":"This dataset was produced within the framework of the Making Electoral Democracy Work project. It contains pre-election and post-election survey data from the 2014 Spanish European election. It covers two regions: Catalonia and Madrid. Making Electoral Democracy Work (MEDW) is an international collaborative project that was conducted between 2009 and 2017 by a large team of political scientists, economists, and psychologists from Canada, Europe, and the United States. Its goal was to examine how the rules of the game (especially the electoral system) and the electoral context (especially the competitiveness and salience of the election) influence the dynamic and reciprocal relationship between voters and parties. To do so, the project gathered data for different types of elections held in Canada, France, Germany, Spain, and Switzerland between 2010 and 2016. In each country, two subnational units, typically regions, were studied. The analyses were complemented by laboratory and online experiments, as well as data on the parties’ campaigns. A selection of the project publications can be found at http://electoraldemocracy.com/publications. For more information on the project visit the project website (http://electoraldemocracy.com) or read André Blais, “Making Electoral Democracy Work,” Electoral Studies 29 (2010): 169–70.\r\n"},"dsDescriptionDate":{"typeName":"dsDescriptionDate","multiple":false,"typeClass":"primitive","value":"2017-08-25"}}]},{"typeName":"subject","multiple":true,"typeClass":"controlledVocabulary","value":["Social Sciences"]},{"typeName":"keyword","multiple":true,"typeClass":"compound","value":[{"keywordValue":{"typeName":"keywordValue","multiple":false,"typeClass":"primitive","value":"Political Behavior"}},{"keywordValue":{"typeName":"keywordValue","multiple":false,"typeClass":"primitive","value":"Elections"}},{"keywordValue":{"typeName":"keywordValue","multiple":false,"typeClass":"primitive","value":"Voting"}},{"keywordValue":{"typeName":"keywordValue","multiple":false,"typeClass":"primitive","value":"Spain"}},{"keywordValue":{"typeName":"keywordValue","multiple":false,"typeClass":"primitive","value":"Mass political attitudes"}}]},{"typeName":"topicClassification","multiple":true,"typeClass":"compound","value":[{"topicClassValue":{"typeName":"topicClassValue","multiple":false,"typeClass":"primitive","value":"Elections"}}]},{"typeName":"language","multiple":true,"typeClass":"controlledVocabulary","value":["Catalan,Valencian","Spanish, Castilian"]},{"typeName":"depositor","multiple":false,"typeClass":"primitive","value":"Kostelka, Filip"},{"typeName":"dateOfDeposit","multiple":false,"typeClass":"primitive","value":"2017-08-23"},{"typeName":"dateOfCollection","multiple":true,"typeClass":"compound","value":[{"dateOfCollectionStart":{"typeName":"dateOfCollectionStart","multiple":false,"typeClass":"primitive","value":"2014-05-12"},"dateOfCollectionEnd":{"typeName":"dateOfCollectionEnd","multiple":false,"typeClass":"primitive","value":"2014-05-20"}},{"dateOfCollectionStart":{"typeName":"dateOfCollectionStart","multiple":false,"typeClass":"primitive","value":"2014-05-26"},"dateOfCollectionEnd":{"typeName":"dateOfCollectionEnd","multiple":false,"typeClass":"primitive","value":"2014-06-10"}}]},{"typeName":"kindOfData","multiple":true,"typeClass":"primitive","value":["Survey data"]},{"typeName":"series","multiple":false,"typeClass":"compound","value":{"seriesName":{"typeName":"seriesName","multiple":false,"typeClass":"primitive","value":"Making Electoral Democracy Work"}}},{"typeName":"software","multiple":true,"typeClass":"compound","value":[{"softwareName":{"typeName":"softwareName","multiple":false,"typeClass":"primitive","value":"Stata"}}]},{"typeName":"relatedDatasets","multiple":true,"typeClass":"primitive","value":["Stephenson, Laura; Blais, André; Bol, Damien; Kostelka, Filip, 2017, \"Making Electoral Democracy Work\", doi:10.7910/DVN/RR0NNQ, Harvard Dataverse."]}]}},"files":[{"description":"Data file - Catalonia","label":"Catalonia_European_2014.tab","restricted":false,"version":2,"datasetVersionId":128384,"dataFile":{"id":3049101,"persistentId":"doi:10.7910/DVN/ZC7SMZ/6RRD5H","pidURL":"https://doi.org/10.7910/DVN/ZC7SMZ/6RRD5H","filename":"Catalonia_European_2014.tab","contentType":"text/tab-separated-values","filesize":811947,"description":"Data file - Catalonia","storageIdentifier":"s3://dvn-cloud:15e12532862-c859f75b4705","originalFileFormat":"application/x-stata","originalFormatLabel":"Stata Binary","UNF":"UNF:6:itOOlLcDfD7yrN37QqzHBQ==","rootDataFileId":-1,"md5":"863ac41478c8a55e172d34404f73f927","checksum":{"type":"MD5","value":"863ac41478c8a55e172d34404f73f927"}}},{"description":"Codebook - Catalonia","label":"Codebook_Catalonia_Europe_2014.xls","restricted":false,"version":1,"datasetVersionId":128384,"dataFile":{"id":3049096,"persistentId":"doi:10.7910/DVN/ZC7SMZ/QY6NOF","pidURL":"https://doi.org/10.7910/DVN/ZC7SMZ/QY6NOF","filename":"Codebook_Catalonia_Europe_2014.xls","contentType":"application/vnd.ms-excel","filesize":300032,"description":"Codebook - Catalonia","storageIdentifier":"s3://dvn-cloud:15e12532e76-f917060337c2","rootDataFileId":-1,"md5":"6f0f23ebb8c0a5986b0f62647df3935f","checksum":{"type":"MD5","value":"6f0f23ebb8c0a5986b0f62647df3935f"}}},{"description":"Codebook - Madrid","label":"Codebook_Madrid_Europe_2014.xls","restricted":false,"version":1,"datasetVersionId":128384,"dataFile":{"id":3049097,"persistentId":"doi:10.7910/DVN/ZC7SMZ/ABNPTG","pidURL":"https://doi.org/10.7910/DVN/ZC7SMZ/ABNPTG","filename":"Codebook_Madrid_Europe_2014.xls","contentType":"application/vnd.ms-excel","filesize":276992,"description":"Codebook - Madrid","storageIdentifier":"s3://dvn-cloud:15e1253332c-7dff2d2d2648","rootDataFileId":-1,"md5":"d4447cf45361c3a9195264acef70e37e","checksum":{"type":"MD5","value":"d4447cf45361c3a9195264acef70e37e"}}},{"description":"Data file - Madrid","label":"Madrid_European_2014.tab","restricted":false,"version":2,"datasetVersionId":128384,"dataFile":{"id":3049099,"persistentId":"doi:10.7910/DVN/ZC7SMZ/ZK9LVH","pidURL":"https://doi.org/10.7910/DVN/ZC7SMZ/ZK9LVH","filename":"Madrid_European_2014.tab","contentType":"text/tab-separated-values","filesize":759359,"description":"Data file - Madrid","storageIdentifier":"s3://dvn-cloud:15e12533a4c-0d2413543971","originalFileFormat":"application/x-stata","originalFormatLabel":"Stata Binary","UNF":"UNF:6:pU4ISi1KxB9Zd1ukIdt9QA==","rootDataFileId":-1,"md5":"a492682e8593206e3f07f188f8343d94","checksum":{"type":"MD5","value":"a492682e8593206e3f07f188f8343d94"}}},{"description":"Questionnaire - Catalonia (in Catalan)","label":"Questionnaire_Catalonia_European_2014_CA.doc","restricted":false,"version":1,"datasetVersionId":128384,"dataFile":{"id":3049098,"persistentId":"doi:10.7910/DVN/ZC7SMZ/VYX8VC","pidURL":"https://doi.org/10.7910/DVN/ZC7SMZ/VYX8VC","filename":"Questionnaire_Catalonia_European_2014_CA.doc","contentType":"application/msword","filesize":442368,"description":"Questionnaire - Catalonia (in Catalan)","storageIdentifier":"s3://dvn-cloud:15e12534028-a7bade3f9c0d","rootDataFileId":-1,"md5":"014dc2f3881fef25e8c21476f1b54308","checksum":{"type":"MD5","value":"014dc2f3881fef25e8c21476f1b54308"}}},{"description":"Questionnaire - Catalonia (in Spanish)","label":"Questionnaire_Catalonia_European_2014_ES.doc","restricted":false,"version":1,"datasetVersionId":128384,"dataFile":{"id":3049100,"persistentId":"doi:10.7910/DVN/ZC7SMZ/RQK30R","pidURL":"https://doi.org/10.7910/DVN/ZC7SMZ/RQK30R","filename":"Questionnaire_Catalonia_European_2014_ES.doc","contentType":"application/msword","filesize":453120,"description":"Questionnaire - Catalonia (in Spanish)","storageIdentifier":"s3://dvn-cloud:15e12534530-d371bbb6effd","rootDataFileId":-1,"md5":"1071e322da64aabcdf5bb6bdb68b381b","checksum":{"type":"MD5","value":"1071e322da64aabcdf5bb6bdb68b381b"}}},{"description":"Questionnaire - Madrid (in Catalan)","label":"Questionnaire_Madrid_European_2014_ES.doc","restricted":false,"version":1,"datasetVersionId":128384,"dataFile":{"id":3049102,"persistentId":"doi:10.7910/DVN/ZC7SMZ/EZLYSV","pidURL":"https://doi.org/10.7910/DVN/ZC7SMZ/EZLYSV","filename":"Questionnaire_Madrid_European_2014_ES.doc","contentType":"application/msword","filesize":441856,"description":"Questionnaire - Madrid (in Catalan)","storageIdentifier":"s3://dvn-cloud:15e12534a69-25217d5d5f36","rootDataFileId":-1,"md5":"be1298126c7bcdd3462c3fe727deccc8","checksum":{"type":"MD5","value":"be1298126c7bcdd3462c3fe727deccc8"}}},{"description":"Readme file","label":"README_Spanish_European_2014.pdf","restricted":false,"version":1,"datasetVersionId":128384,"dataFile":{"id":3049104,"persistentId":"doi:10.7910/DVN/ZC7SMZ/LIRW9K","pidURL":"https://doi.org/10.7910/DVN/ZC7SMZ/LIRW9K","filename":"README_Spanish_European_2014.pdf","contentType":"application/pdf","filesize":265208,"description":"Readme file","storageIdentifier":"s3://dvn-cloud:15e125be334-5de8dbbf47b7","rootDataFileId":-1,"md5":"81c322d163ddff4ef7f13e02bc9ad47d","checksum":{"type":"MD5","value":"81c322d163ddff4ef7f13e02bc9ad47d"}}},{"description":"Technical report","label":"Technical_Report_MEDW_European_2014.docx","restricted":false,"version":1,"datasetVersionId":128384,"dataFile":{"id":3049103,"persistentId":"doi:10.7910/DVN/ZC7SMZ/1RYPSI","pidURL":"https://doi.org/10.7910/DVN/ZC7SMZ/1RYPSI","filename":"Technical_Report_MEDW_European_2014.docx","contentType":"application/vnd.openxmlformats-officedocument.wordprocessingml.document","filesize":1529184,"description":"Technical report","storageIdentifier":"s3://dvn-cloud:15e1253501d-cd74370d5edd","rootDataFileId":-1,"md5":"cb2dae5f6442944bd90ed014811e41d3","checksum":{"type":"MD5","value":"cb2dae5f6442944bd90ed014811e41d3"}}}]}}}