{"status":"OK","data":{"id":2808781,"identifier":"DVN/XRIOXT","persistentUrl":"https://doi.org/10.7910/DVN/XRIOXT","protocol":"doi","authority":"10.7910","publisher":"Harvard Dataverse","publicationDate":"2016-05-01","storageIdentifier":"s3://dvn-cloud:10.7910/DVN/XRIOXT","latestVersion":{"id":81428,"storageIdentifier":"s3://dvn-cloud:10.7910/DVN/XRIOXT","versionNumber":1,"versionMinorNumber":1,"versionState":"RELEASED","productionDate":"Production Date","lastUpdateTime":"2016-05-02T06:04:51Z","releaseTime":"2016-05-02T06:04:51Z","createTime":"2016-05-02T06:04:46Z","license":"CC0","termsOfUse":"CC0 Waiver","metadataBlocks":{"citation":{"displayName":"Citation Metadata","fields":[{"typeName":"title","multiple":false,"typeClass":"primitive","value":"Arno Klein Presentations on Visualization"},{"typeName":"author","multiple":true,"typeClass":"compound","value":[{"authorName":{"typeName":"authorName","multiple":false,"typeClass":"primitive","value":"Klein, Arno"},"authorIdentifierScheme":{"typeName":"authorIdentifierScheme","multiple":false,"typeClass":"controlledVocabulary","value":"ORCID"},"authorIdentifier":{"typeName":"authorIdentifier","multiple":false,"typeClass":"primitive","value":"0000-0002-0707-2889"}}]},{"typeName":"datasetContact","multiple":true,"typeClass":"compound","value":[{"datasetContactName":{"typeName":"datasetContactName","multiple":false,"typeClass":"primitive","value":"Klein, Arno"},"datasetContactEmail":{"typeName":"datasetContactEmail","multiple":false,"typeClass":"primitive","value":"arno@binarybottle.com"}}]},{"typeName":"dsDescription","multiple":true,"typeClass":"compound","value":[{"dsDescriptionValue":{"typeName":"dsDescriptionValue","multiple":false,"typeClass":"primitive","value":"Arno Klein's papers on visualization, including the elloracaves.org cave temple documentation and web application, and the elloradaily.info time-lapse project."}}]},{"typeName":"subject","multiple":true,"typeClass":"controlledVocabulary","value":["Arts and Humanities","Computer and Information Science","Other"]},{"typeName":"depositor","multiple":false,"typeClass":"primitive","value":"Klein, Arno"},{"typeName":"dateOfDeposit","multiple":false,"typeClass":"primitive","value":"2016-05-01"}]}},"files":[{"label":"Dorkbot_ElloraCaves_20130203_LONG.pdf","restricted":false,"version":1,"datasetVersionId":81428,"categories":["Slides"],"dataFile":{"id":2808849,"persistentId":"doi:10.7910/DVN/XRIOXT/9HZTZP","pidURL":"https://doi.org/10.7910/DVN/XRIOXT/9HZTZP","filename":"Dorkbot_ElloraCaves_20130203_LONG.pdf","contentType":"application/pdf","filesize":113711411,"storageIdentifier":"s3://dvn-cloud:1546f06c3b2-dd062172dbf8","rootDataFileId":-1,"md5":"e4f596d056563c94f08a3876a5a98ce1","checksum":{"type":"MD5","value":"e4f596d056563c94f08a3876a5a98ce1"}}},{"label":"Dorkbot_ElloraCaves_20130206.pdf","restricted":false,"version":1,"datasetVersionId":81428,"categories":["Slides"],"dataFile":{"id":2808848,"persistentId":"doi:10.7910/DVN/XRIOXT/NUBSB9","pidURL":"https://doi.org/10.7910/DVN/XRIOXT/NUBSB9","filename":"Dorkbot_ElloraCaves_20130206.pdf","contentType":"application/pdf","filesize":87380067,"storageIdentifier":"s3://dvn-cloud:1546f03bf40-043e6634ee81","rootDataFileId":-1,"md5":"0b83936e6e58a5d7ca80ddf334e43f9e","checksum":{"type":"MD5","value":"0b83936e6e58a5d7ca80ddf334e43f9e"}}},{"label":"Dorkbot_ElloraDailyPhoto_20120201_no_movie.pdf","restricted":false,"version":1,"datasetVersionId":81428,"categories":["Slides"],"dataFile":{"id":2808850,"persistentId":"doi:10.7910/DVN/XRIOXT/RUFPVC","pidURL":"https://doi.org/10.7910/DVN/XRIOXT/RUFPVC","filename":"Dorkbot_ElloraDailyPhoto_20120201_no_movie.pdf","contentType":"application/pdf","filesize":17789382,"storageIdentifier":"s3://dvn-cloud:1546f0ffc9f-0ac8678b7c9d","rootDataFileId":-1,"md5":"731015611983843d8ca10137bf7ad671","checksum":{"type":"MD5","value":"731015611983843d8ca10137bf7ad671"}}},{"label":"ElloraCaves_20110225.pdf","restricted":false,"version":1,"datasetVersionId":81428,"categories":["Slides"],"dataFile":{"id":2808846,"persistentId":"doi:10.7910/DVN/XRIOXT/HDXJ1Y","pidURL":"https://doi.org/10.7910/DVN/XRIOXT/HDXJ1Y","filename":"ElloraCaves_20110225.pdf","contentType":"application/pdf","filesize":16653297,"storageIdentifier":"s3://dvn-cloud:1546f02c2ba-666b6920e1f4","rootDataFileId":-1,"md5":"51541632977a7df0763c86bcf9904478","checksum":{"type":"MD5","value":"51541632977a7df0763c86bcf9904478"}}},{"label":"Ellora_project_20051027.pdf","restricted":false,"version":1,"datasetVersionId":81428,"categories":["Slides"],"dataFile":{"id":2808847,"persistentId":"doi:10.7910/DVN/XRIOXT/44QSBU","pidURL":"https://doi.org/10.7910/DVN/XRIOXT/44QSBU","filename":"Ellora_project_20051027.pdf","contentType":"application/pdf","filesize":8918303,"storageIdentifier":"s3://dvn-cloud:1546f0333c4-293eaee550e8","rootDataFileId":-1,"md5":"f64fb290afa9e4ca9645808d2a57d024","checksum":{"type":"MD5","value":"f64fb290afa9e4ca9645808d2a57d024"}}}]}}}