{"status":"OK","data":{"id":2966338,"identifier":"DVN/7LZBD3","persistentUrl":"https://doi.org/10.7910/DVN/7LZBD3","protocol":"doi","authority":"10.7910","publisher":"Harvard Dataverse","publicationDate":"2016-12-22","storageIdentifier":"s3://dvn-cloud:10.7910/DVN/7LZBD3","latestVersion":{"id":96812,"storageIdentifier":"s3://dvn-cloud:10.7910/DVN/7LZBD3","versionNumber":1,"versionMinorNumber":0,"versionState":"RELEASED","productionDate":"Production Date","UNF":"UNF:6:CcNDXKA2jjhaoE19W9A4Sg==","lastUpdateTime":"2016-12-22T06:46:20Z","releaseTime":"2016-12-22T06:46:20Z","createTime":"2016-12-20T22:03:23Z","license":"CC0","termsOfUse":"CC0 Waiver","metadataBlocks":{"citation":{"displayName":"Citation Metadata","fields":[{"typeName":"title","multiple":false,"typeClass":"primitive","value":"Measurements in support of 10-Month Characterization of the Aerosol Number Size Distribution and Related Air Quality and Meteorology at the Bondville, IL Midwestern Background Site"},{"typeName":"author","multiple":true,"typeClass":"compound","value":[{"authorName":{"typeName":"authorName","multiple":false,"typeClass":"primitive","value":"Stanier, Charles"},"authorAffiliation":{"typeName":"authorAffiliation","multiple":false,"typeClass":"primitive","value":"University of Iowa"},"authorIdentifierScheme":{"typeName":"authorIdentifierScheme","multiple":false,"typeClass":"controlledVocabulary","value":"ORCID"},"authorIdentifier":{"typeName":"authorIdentifier","multiple":false,"typeClass":"primitive","value":"0000-0001-9924-0853"}},{"authorName":{"typeName":"authorName","multiple":false,"typeClass":"primitive","value":"Bullard, Robert"},"authorAffiliation":{"typeName":"authorAffiliation","multiple":false,"typeClass":"primitive","value":"Brookhaven National Laboratory"}},{"authorName":{"typeName":"authorName","multiple":false,"typeClass":"primitive","value":"Singh, Ashish"},"authorAffiliation":{"typeName":"authorAffiliation","multiple":false,"typeClass":"primitive","value":"University of Iowa"}}]},{"typeName":"datasetContact","multiple":true,"typeClass":"compound","value":[{"datasetContactName":{"typeName":"datasetContactName","multiple":false,"typeClass":"primitive","value":"Stanier, Charles"},"datasetContactAffiliation":{"typeName":"datasetContactAffiliation","multiple":false,"typeClass":"primitive","value":"University of Iowa"},"datasetContactEmail":{"typeName":"datasetContactEmail","multiple":false,"typeClass":"primitive","value":"charles-stanier@uiowa.edu"}}]},{"typeName":"dsDescription","multiple":true,"typeClass":"compound","value":[{"dsDescriptionValue":{"typeName":"dsDescriptionValue","multiple":false,"typeClass":"primitive","value":"This entry contains measurement data in support of the paper Bullard et al. 10-Month Characterization of the Aerosol Number Size Distribution and Related Air Quality and Meteorology at the Bondville, IL Midwestern Background Site.  at the time of data upload, the paper was in review at Atmospheric Environment.  Please search for the final bibliographic data.  We anticipate a 2017 year of publication for the data.\r\n\r\nThe measurements run from June 2013 - July 2014 and feature aerosol size distribution (3 nm - 2500 nm) and related gases. "},"dsDescriptionDate":{"typeName":"dsDescriptionDate","multiple":false,"typeClass":"primitive","value":"2016-12-20"}}]},{"typeName":"subject","multiple":true,"typeClass":"controlledVocabulary","value":["Earth and Environmental Sciences","Engineering"]},{"typeName":"keyword","multiple":true,"typeClass":"compound","value":[{"keywordValue":{"typeName":"keywordValue","multiple":false,"typeClass":"primitive","value":"Aerosol"}},{"keywordValue":{"typeName":"keywordValue","multiple":false,"typeClass":"primitive","value":"Ultrafine Particles"}},{"keywordValue":{"typeName":"keywordValue","multiple":false,"typeClass":"primitive","value":"Nucleation"}},{"keywordValue":{"typeName":"keywordValue","multiple":false,"typeClass":"primitive","value":"Bondville"}},{"keywordValue":{"typeName":"keywordValue","multiple":false,"typeClass":"primitive","value":"PM2.5"}},{"keywordValue":{"typeName":"keywordValue","multiple":false,"typeClass":"primitive","value":"Air Quality"}},{"keywordValue":{"typeName":"keywordValue","multiple":false,"typeClass":"primitive","value":"Air Pollution"}},{"keywordValue":{"typeName":"keywordValue","multiple":false,"typeClass":"primitive","value":"Number Size Distribution"}}]},{"typeName":"grantNumber","multiple":true,"typeClass":"compound","value":[{"grantNumberAgency":{"typeName":"grantNumberAgency","multiple":false,"typeClass":"primitive","value":"NSF"},"grantNumberValue":{"typeName":"grantNumberValue","multiple":false,"typeClass":"primitive","value":"ATM-0748602 "}}]},{"typeName":"depositor","multiple":false,"typeClass":"primitive","value":"Stanier, Charles"},{"typeName":"dateOfDeposit","multiple":false,"typeClass":"primitive","value":"2016-12-20"},{"typeName":"timePeriodCovered","multiple":true,"typeClass":"compound","value":[{"timePeriodCoveredStart":{"typeName":"timePeriodCoveredStart","multiple":false,"typeClass":"primitive","value":"2013-07-01"},"timePeriodCoveredEnd":{"typeName":"timePeriodCoveredEnd","multiple":false,"typeClass":"primitive","value":"2014-06-30"}}]},{"typeName":"dateOfCollection","multiple":true,"typeClass":"compound","value":[{"dateOfCollectionStart":{"typeName":"dateOfCollectionStart","multiple":false,"typeClass":"primitive","value":"2013-07-01"},"dateOfCollectionEnd":{"typeName":"dateOfCollectionEnd","multiple":false,"typeClass":"primitive","value":"2014-06-30"}}]},{"typeName":"kindOfData","multiple":true,"typeClass":"primitive","value":["Atmospheric Composition and Meteorology"]}]}},"files":[{"description":"Documentation, data and metadeta","label":"stanier_bondville_for_archive_v1_2016_12_22.tab","restricted":false,"version":2,"datasetVersionId":96812,"dataFile":{"id":2966513,"persistentId":"doi:10.7910/DVN/7LZBD3/QUL4LP","pidURL":"https://doi.org/10.7910/DVN/7LZBD3/QUL4LP","filename":"stanier_bondville_for_archive_v1_2016_12_22.tab","contentType":"text/tab-separated-values","filesize":556,"description":"Documentation, data and metadeta","storageIdentifier":"s3://dvn-cloud:1592541e581-627538af83b0","originalFileFormat":"application/vnd.openxmlformats-officedocument.spreadsheetml.sheet","originalFormatLabel":"MS Excel (XLSX)","UNF":"UNF:6:CcNDXKA2jjhaoE19W9A4Sg==","rootDataFileId":-1,"md5":"2a2397790dc4fffd8b418aab38b557a3","checksum":{"type":"MD5","value":"2a2397790dc4fffd8b418aab38b557a3"}}}]}}}