{"status":"OK","data":{"id":64291,"identifier":"DVN/PI607","persistentUrl":"https://doi.org/10.7910/DVN/PI607","protocol":"doi","authority":"10.7910","publisher":"Harvard Dataverse","publicationDate":"2015-02-11","storageIdentifier":"s3://dvn-cloud:10.7910/DVN/PI607","latestVersion":{"id":121439,"storageIdentifier":"s3://dvn-cloud:10.7910/DVN/PI607","versionNumber":4,"versionMinorNumber":0,"versionState":"RELEASED","productionDate":"Production Date","lastUpdateTime":"2017-02-05T23:42:46Z","releaseTime":"2017-02-05T23:42:46Z","createTime":"2017-02-05T23:42:30Z","license":"NONE","metadataBlocks":{"citation":{"displayName":"Citation Metadata","fields":[{"typeName":"title","multiple":false,"typeClass":"primitive","value":"House Unpassed Legislation 1848, Docket 2157, SC1/series 230, Petition of Wendell Phillips"},{"typeName":"author","multiple":true,"typeClass":"compound","value":[{"authorName":{"typeName":"authorName","multiple":false,"typeClass":"primitive","value":"Digital Archive of Massachusetts Anti-Slavery and Anti-Segregation Petitions, Massachusetts Archives, Boston MA"}}]},{"typeName":"datasetContact","multiple":true,"typeClass":"compound","value":[{"datasetContactEmail":{"typeName":"datasetContactEmail","multiple":false,"typeClass":"primitive","value":"dcarpenter@gov.harvard.edu"}}]},{"typeName":"dsDescription","multiple":true,"typeClass":"compound","value":[{"dsDescriptionValue":{"typeName":"dsDescriptionValue","multiple":false,"typeClass":"primitive","value":"<p>Petition subject: Abolition of capital punishment </p> <p>Original: <a href=\"http://nrs.harvard.edu/urn-3:FHCL:13481428\">http://nrs.harvard.edu/urn-3:FHCL:13481428</a> </p> <p>Date of creation: (unknown) </p> <p>Petition location: Massachusetts </p> <p>Legislator, committee, or address that the petition was sent to: Several names from a committee </p> <p>Selected signatures:<ol><li>Wendell Phillips</li><li>Ann G. Phillips</li><li>Mary G. Chapman</li><li>Deborah Weston</li><li>Elizabeth B. Chapman</li><li>Maria Weston Chapman</li><li>Sarah Trask</li><li>H.G. Chapman</li><li>Nancy Twombly</li><li>Lucia Weston</li><li>Mary Greene</li><li>Mary Neal</li><li>Elizabeth Burke</li><li>Ellen Garde</li><li>Mary Ann Cross</li><li>H.B. Emerson</li><li>Elizabeth Mills</li><li>Catherine Rigney</li><li>Bridget Ward</li><li>Christianna Spear</li><li>Catherine Brickley</li><li>Hannah Luscomb</li><li>Bridget Quinn</li><li>Mary Jane Johnson</li><li>Jane Solomon</li><li>Helen E. Garrison</li><li>Anna M. Grafton</li><li>Charles C. Follen</li><li>Anne Warren Weston</li><li>Caroline Weston</li><li>Frances Mary Robbins</li><li>Hervey E. Weston</li><li>Mary May</li><li>Sarah D. Robinson</li><li>Elizabeth Goddard</li><li>Mary C. Blanchard</li><li>Anna W. Cotton</li><li>Margaret H. Hunt</li><li>Edward Colman</li><li>Robert F. Wallcut</li><li>Samuel May Jr.</li><li>William Lloyd Garrison</li><li>Daniel F. Child</li><li>Catharine Sargent</li><li>Jane Clifford</li></ol> </p> <p>Actions taken on dates: 1848-02-12 </p> <p>Legislative action: Received in the House on February 12, 1848 and referred to a committee </p> <p>Total signatures: 69 </p> <p>Legislative action summary: Received, referred </p> <p>Legal voter signatures (males not identified as non-legal): 11 </p> <p>Female signatures: 52 </p> <p>Unidentified signatures: 6 </p> <p>Female only signatures: No </p> <p>Identifications of signatories: undersigned, [females], [\"others]\" </p> <p>Prayer format was <a href=\"http://en.wikipedia.org/wiki/Printing\">printed</a> vs. <a href=\"http://en.wikipedia.org/wiki/Manuscript\">manuscript</a>: Printed </p> <p>Signatory column format: not column separated </p> <p>Additional non-petition or unrelated documents available at archive: no additional documents </p> <p>Additional archivist notes: [Petition wrapper with the petition of Joshua Wilder] </p> <p>Location of the petition at the Massachusetts Archives of the Commonwealth: House Unpassed 1848, Docket 2157 </p> <p>Acknowledgements: Supported by the National Endowment for the Humanities (PW-5105612), Massachusetts Archives of the Commonwealth, Radcliffe Institute for Advanced Study at Harvard University, Center for American Political Studies at Harvard University, Institutional Development Initiative at Harvard University, and Harvard University Library.</p>"}}]},{"typeName":"subject","multiple":true,"typeClass":"controlledVocabulary","value":["Social Sciences"]},{"typeName":"keyword","multiple":true,"typeClass":"compound","value":[{"keywordValue":{"typeName":"keywordValue","multiple":false,"typeClass":"primitive","value":"received"},"keywordVocabulary":{"typeName":"keywordVocabulary","multiple":false,"typeClass":"primitive","value":"action"}},{"keywordValue":{"typeName":"keywordValue","multiple":false,"typeClass":"primitive","value":"referred"},"keywordVocabulary":{"typeName":"keywordVocabulary","multiple":false,"typeClass":"primitive","value":"action"}},{"keywordValue":{"typeName":"keywordValue","multiple":false,"typeClass":"primitive","value":"Printed"},"keywordVocabulary":{"typeName":"keywordVocabulary","multiple":false,"typeClass":"primitive","value":"prayer-format"}},{"keywordValue":{"typeName":"keywordValue","multiple":false,"typeClass":"primitive","value":"Several names from a committee"},"keywordVocabulary":{"typeName":"keywordVocabulary","multiple":false,"typeClass":"primitive","value":"sent"}},{"keywordValue":{"typeName":"keywordValue","multiple":false,"typeClass":"primitive","value":"Ann G. Phillips"},"keywordVocabulary":{"typeName":"keywordVocabulary","multiple":false,"typeClass":"primitive","value":"signatory"}},{"keywordValue":{"typeName":"keywordValue","multiple":false,"typeClass":"primitive","value":"Anna M. Grafton"},"keywordVocabulary":{"typeName":"keywordVocabulary","multiple":false,"typeClass":"primitive","value":"signatory"}},{"keywordValue":{"typeName":"keywordValue","multiple":false,"typeClass":"primitive","value":"Anna W. Cotton"},"keywordVocabulary":{"typeName":"keywordVocabulary","multiple":false,"typeClass":"primitive","value":"signatory"}},{"keywordValue":{"typeName":"keywordValue","multiple":false,"typeClass":"primitive","value":"Anne Warren Weston"},"keywordVocabulary":{"typeName":"keywordVocabulary","multiple":false,"typeClass":"primitive","value":"signatory"}},{"keywordValue":{"typeName":"keywordValue","multiple":false,"typeClass":"primitive","value":"Bridget Quinn"},"keywordVocabulary":{"typeName":"keywordVocabulary","multiple":false,"typeClass":"primitive","value":"signatory"}},{"keywordValue":{"typeName":"keywordValue","multiple":false,"typeClass":"primitive","value":"Bridget Ward"},"keywordVocabulary":{"typeName":"keywordVocabulary","multiple":false,"typeClass":"primitive","value":"signatory"}},{"keywordValue":{"typeName":"keywordValue","multiple":false,"typeClass":"primitive","value":"Caroline Weston"},"keywordVocabulary":{"typeName":"keywordVocabulary","multiple":false,"typeClass":"primitive","value":"signatory"}},{"keywordValue":{"typeName":"keywordValue","multiple":false,"typeClass":"primitive","value":"Catharine Sargent"},"keywordVocabulary":{"typeName":"keywordVocabulary","multiple":false,"typeClass":"primitive","value":"signatory"}},{"keywordValue":{"typeName":"keywordValue","multiple":false,"typeClass":"primitive","value":"Catherine Brickley"},"keywordVocabulary":{"typeName":"keywordVocabulary","multiple":false,"typeClass":"primitive","value":"signatory"}},{"keywordValue":{"typeName":"keywordValue","multiple":false,"typeClass":"primitive","value":"Catherine Rigney"},"keywordVocabulary":{"typeName":"keywordVocabulary","multiple":false,"typeClass":"primitive","value":"signatory"}},{"keywordValue":{"typeName":"keywordValue","multiple":false,"typeClass":"primitive","value":"Charles C. Follen"},"keywordVocabulary":{"typeName":"keywordVocabulary","multiple":false,"typeClass":"primitive","value":"signatory"}},{"keywordValue":{"typeName":"keywordValue","multiple":false,"typeClass":"primitive","value":"Christianna Spear"},"keywordVocabulary":{"typeName":"keywordVocabulary","multiple":false,"typeClass":"primitive","value":"signatory"}},{"keywordValue":{"typeName":"keywordValue","multiple":false,"typeClass":"primitive","value":"Daniel F. Child"},"keywordVocabulary":{"typeName":"keywordVocabulary","multiple":false,"typeClass":"primitive","value":"signatory"}},{"keywordValue":{"typeName":"keywordValue","multiple":false,"typeClass":"primitive","value":"Deborah Weston"},"keywordVocabulary":{"typeName":"keywordVocabulary","multiple":false,"typeClass":"primitive","value":"signatory"}},{"keywordValue":{"typeName":"keywordValue","multiple":false,"typeClass":"primitive","value":"Edward Colman"},"keywordVocabulary":{"typeName":"keywordVocabulary","multiple":false,"typeClass":"primitive","value":"signatory"}},{"keywordValue":{"typeName":"keywordValue","multiple":false,"typeClass":"primitive","value":"Elizabeth B. Chapman"},"keywordVocabulary":{"typeName":"keywordVocabulary","multiple":false,"typeClass":"primitive","value":"signatory"}},{"keywordValue":{"typeName":"keywordValue","multiple":false,"typeClass":"primitive","value":"Elizabeth Burke"},"keywordVocabulary":{"typeName":"keywordVocabulary","multiple":false,"typeClass":"primitive","value":"signatory"}},{"keywordValue":{"typeName":"keywordValue","multiple":false,"typeClass":"primitive","value":"Elizabeth Goddard"},"keywordVocabulary":{"typeName":"keywordVocabulary","multiple":false,"typeClass":"primitive","value":"signatory"}},{"keywordValue":{"typeName":"keywordValue","multiple":false,"typeClass":"primitive","value":"Elizabeth Mills"},"keywordVocabulary":{"typeName":"keywordVocabulary","multiple":false,"typeClass":"primitive","value":"signatory"}},{"keywordValue":{"typeName":"keywordValue","multiple":false,"typeClass":"primitive","value":"Ellen Garde"},"keywordVocabulary":{"typeName":"keywordVocabulary","multiple":false,"typeClass":"primitive","value":"signatory"}},{"keywordValue":{"typeName":"keywordValue","multiple":false,"typeClass":"primitive","value":"Frances Mary Robbins"},"keywordVocabulary":{"typeName":"keywordVocabulary","multiple":false,"typeClass":"primitive","value":"signatory"}},{"keywordValue":{"typeName":"keywordValue","multiple":false,"typeClass":"primitive","value":"H.B. Emerson"},"keywordVocabulary":{"typeName":"keywordVocabulary","multiple":false,"typeClass":"primitive","value":"signatory"}},{"keywordValue":{"typeName":"keywordValue","multiple":false,"typeClass":"primitive","value":"H.G. Chapman"},"keywordVocabulary":{"typeName":"keywordVocabulary","multiple":false,"typeClass":"primitive","value":"signatory"}},{"keywordValue":{"typeName":"keywordValue","multiple":false,"typeClass":"primitive","value":"Hannah Luscomb"},"keywordVocabulary":{"typeName":"keywordVocabulary","multiple":false,"typeClass":"primitive","value":"signatory"}},{"keywordValue":{"typeName":"keywordValue","multiple":false,"typeClass":"primitive","value":"Helen E. Garrison"},"keywordVocabulary":{"typeName":"keywordVocabulary","multiple":false,"typeClass":"primitive","value":"signatory"}},{"keywordValue":{"typeName":"keywordValue","multiple":false,"typeClass":"primitive","value":"Hervey E. Weston"},"keywordVocabulary":{"typeName":"keywordVocabulary","multiple":false,"typeClass":"primitive","value":"signatory"}},{"keywordValue":{"typeName":"keywordValue","multiple":false,"typeClass":"primitive","value":"Jane Clifford"},"keywordVocabulary":{"typeName":"keywordVocabulary","multiple":false,"typeClass":"primitive","value":"signatory"}},{"keywordValue":{"typeName":"keywordValue","multiple":false,"typeClass":"primitive","value":"Jane Solomon"},"keywordVocabulary":{"typeName":"keywordVocabulary","multiple":false,"typeClass":"primitive","value":"signatory"}},{"keywordValue":{"typeName":"keywordValue","multiple":false,"typeClass":"primitive","value":"Lucia Weston"},"keywordVocabulary":{"typeName":"keywordVocabulary","multiple":false,"typeClass":"primitive","value":"signatory"}},{"keywordValue":{"typeName":"keywordValue","multiple":false,"typeClass":"primitive","value":"Margaret H. Hunt"},"keywordVocabulary":{"typeName":"keywordVocabulary","multiple":false,"typeClass":"primitive","value":"signatory"}},{"keywordValue":{"typeName":"keywordValue","multiple":false,"typeClass":"primitive","value":"Maria Weston Chapman"},"keywordVocabulary":{"typeName":"keywordVocabulary","multiple":false,"typeClass":"primitive","value":"signatory"}},{"keywordValue":{"typeName":"keywordValue","multiple":false,"typeClass":"primitive","value":"Mary Ann Cross"},"keywordVocabulary":{"typeName":"keywordVocabulary","multiple":false,"typeClass":"primitive","value":"signatory"}},{"keywordValue":{"typeName":"keywordValue","multiple":false,"typeClass":"primitive","value":"Mary C. Blanchard"},"keywordVocabulary":{"typeName":"keywordVocabulary","multiple":false,"typeClass":"primitive","value":"signatory"}},{"keywordValue":{"typeName":"keywordValue","multiple":false,"typeClass":"primitive","value":"Mary G. Chapman"},"keywordVocabulary":{"typeName":"keywordVocabulary","multiple":false,"typeClass":"primitive","value":"signatory"}},{"keywordValue":{"typeName":"keywordValue","multiple":false,"typeClass":"primitive","value":"Mary Greene"},"keywordVocabulary":{"typeName":"keywordVocabulary","multiple":false,"typeClass":"primitive","value":"signatory"}},{"keywordValue":{"typeName":"keywordValue","multiple":false,"typeClass":"primitive","value":"Mary Jane Johnson"},"keywordVocabulary":{"typeName":"keywordVocabulary","multiple":false,"typeClass":"primitive","value":"signatory"}},{"keywordValue":{"typeName":"keywordValue","multiple":false,"typeClass":"primitive","value":"Mary May"},"keywordVocabulary":{"typeName":"keywordVocabulary","multiple":false,"typeClass":"primitive","value":"signatory"}},{"keywordValue":{"typeName":"keywordValue","multiple":false,"typeClass":"primitive","value":"Mary Neal"},"keywordVocabulary":{"typeName":"keywordVocabulary","multiple":false,"typeClass":"primitive","value":"signatory"}},{"keywordValue":{"typeName":"keywordValue","multiple":false,"typeClass":"primitive","value":"Nancy Twombly"},"keywordVocabulary":{"typeName":"keywordVocabulary","multiple":false,"typeClass":"primitive","value":"signatory"}},{"keywordValue":{"typeName":"keywordValue","multiple":false,"typeClass":"primitive","value":"Robert F. Wallcut"},"keywordVocabulary":{"typeName":"keywordVocabulary","multiple":false,"typeClass":"primitive","value":"signatory"}},{"keywordValue":{"typeName":"keywordValue","multiple":false,"typeClass":"primitive","value":"Samuel May Jr."},"keywordVocabulary":{"typeName":"keywordVocabulary","multiple":false,"typeClass":"primitive","value":"signatory"}},{"keywordValue":{"typeName":"keywordValue","multiple":false,"typeClass":"primitive","value":"Sarah D. Robinson"},"keywordVocabulary":{"typeName":"keywordVocabulary","multiple":false,"typeClass":"primitive","value":"signatory"}},{"keywordValue":{"typeName":"keywordValue","multiple":false,"typeClass":"primitive","value":"Sarah Trask"},"keywordVocabulary":{"typeName":"keywordVocabulary","multiple":false,"typeClass":"primitive","value":"signatory"}},{"keywordValue":{"typeName":"keywordValue","multiple":false,"typeClass":"primitive","value":"Wendell Phillips"},"keywordVocabulary":{"typeName":"keywordVocabulary","multiple":false,"typeClass":"primitive","value":"signatory"}},{"keywordValue":{"typeName":"keywordValue","multiple":false,"typeClass":"primitive","value":"William Lloyd Garrison"},"keywordVocabulary":{"typeName":"keywordVocabulary","multiple":false,"typeClass":"primitive","value":"signatory"}},{"keywordValue":{"typeName":"keywordValue","multiple":false,"typeClass":"primitive","value":"["},"keywordVocabulary":{"typeName":"keywordVocabulary","multiple":false,"typeClass":"primitive","value":"signatory-category"}},{"keywordValue":{"typeName":"keywordValue","multiple":false,"typeClass":"primitive","value":"females"},"keywordVocabulary":{"typeName":"keywordVocabulary","multiple":false,"typeClass":"primitive","value":"signatory-category"}},{"keywordValue":{"typeName":"keywordValue","multiple":false,"typeClass":"primitive","value":"undersigned"},"keywordVocabulary":{"typeName":"keywordVocabulary","multiple":false,"typeClass":"primitive","value":"signatory-category"}},{"keywordValue":{"typeName":"keywordValue","multiple":false,"typeClass":"primitive","value":"not column separated"},"keywordVocabulary":{"typeName":"keywordVocabulary","multiple":false,"typeClass":"primitive","value":"signatory-column-format"}},{"keywordValue":{"typeName":"keywordValue","multiple":false,"typeClass":"primitive","value":"No"},"keywordVocabulary":{"typeName":"keywordVocabulary","multiple":false,"typeClass":"primitive","value":"signatures-female-only"}},{"keywordValue":{"typeName":"keywordValue","multiple":false,"typeClass":"primitive","value":"52"},"keywordVocabulary":{"typeName":"keywordVocabulary","multiple":false,"typeClass":"primitive","value":"signatures-females"}},{"keywordValue":{"typeName":"keywordValue","multiple":false,"typeClass":"primitive","value":"11"},"keywordVocabulary":{"typeName":"keywordVocabulary","multiple":false,"typeClass":"primitive","value":"signatures-legal-voters"}},{"keywordValue":{"typeName":"keywordValue","multiple":false,"typeClass":"primitive","value":"69"},"keywordVocabulary":{"typeName":"keywordVocabulary","multiple":false,"typeClass":"primitive","value":"signatures-total"}},{"keywordValue":{"typeName":"keywordValue","multiple":false,"typeClass":"primitive","value":"6"},"keywordVocabulary":{"typeName":"keywordVocabulary","multiple":false,"typeClass":"primitive","value":"signatures-unidentified"}}]},{"typeName":"publication","multiple":true,"typeClass":"compound","value":[{"publicationCitation":{"typeName":"publicationCitation","multiple":false,"typeClass":"primitive","value":"D. Carpenter, N. Topich and G. Griffin. Digital Archive of Massachusetts Anti-Slavery and Anti-Segregation Petitions; House Unpassed Legislation 1848, Docket 2157, SC1/series 230. Massachusetts Archives. Boston, Mass."},"publicationURL":{"typeName":"publicationURL","multiple":false,"typeClass":"primitive","value":"http://nrs.harvard.edu/urn-3:FHCL:13481428"}}]},{"typeName":"distributor","multiple":true,"typeClass":"compound","value":[{"distributorName":{"typeName":"distributorName","multiple":false,"typeClass":"primitive","value":"Massachusetts Archives. Boston, Mass."}},{"distributorName":{"typeName":"distributorName","multiple":false,"typeClass":"primitive","value":"Harvard Dataverse Network"}}]},{"typeName":"dateOfDeposit","multiple":false,"typeClass":"primitive","value":"2017-02-05"},{"typeName":"timePeriodCovered","multiple":true,"typeClass":"compound","value":[{"timePeriodCoveredStart":{"typeName":"timePeriodCoveredStart","multiple":false,"typeClass":"primitive","value":"1848-02-12"},"timePeriodCoveredEnd":{"typeName":"timePeriodCoveredEnd","multiple":false,"typeClass":"primitive","value":"1848-02-12"}}]}]},"geospatial":{"displayName":"Geospatial Metadata","fields":[{"typeName":"geographicCoverage","multiple":true,"typeClass":"compound","value":[{"country":{"typeName":"country","multiple":false,"typeClass":"controlledVocabulary","value":"United States"},"city":{"typeName":"city","multiple":false,"typeClass":"primitive","value":"Massachusetts"}}]}]}},"files":[{"description":"","label":"petitions.xlsx","restricted":false,"directoryLabel":"input_2016-11-18","version":1,"datasetVersionId":121439,"dataFile":{"id":2997034,"persistentId":"doi:10.7910/DVN/PI607/PI8KUI","pidURL":"https://doi.org/10.7910/DVN/PI607/PI8KUI","filename":"petitions.xlsx","contentType":"application/vnd.openxmlformats-officedocument.spreadsheetml.sheet","filesize":1226912,"description":"","storageIdentifier":"s3://dvn-cloud:15a10a86bb5-db08970ff2ab","rootDataFileId":-1,"md5":"1abc747829719298fb777cf92b8285ca","checksum":{"type":"MD5","value":"1abc747829719298fb777cf92b8285ca"}}}]}}}